Metadata-Version: 2.1
Name: git-alias
Version: 0.0.2
Summary: Tools for managing git aliases
Home-page: https://github.com/larsks/git-alias/
Author: Lars Kellogg-Stedman
Author-email: lars@oddbit.com
License: UNKNOWN
Platform: UNKNOWN
